BigDFT/Atoms.py
BigDFT/BZ.py
BigDFT/BioQM.py
BigDFT/CDFT.py
BigDFT/Calculators.py
BigDFT/Datasets.py
BigDFT/DoS.py
BigDFT/Fragments.py
BigDFT/IO.py
BigDFT/InputActions.py
BigDFT/Inputfiles.py
BigDFT/LRTDDFT.py
BigDFT/LogUtils.py
BigDFT/Logfiles.py
BigDFT/PDoS.py
BigDFT/PointParticles.py
BigDFT/PostProcessing.py
BigDFT/Spillage.py
BigDFT/Stats.py
BigDFT/Systems.py
BigDFT/TB.py
BigDFT/UnitCells.py
BigDFT/Visualization.py
BigDFT/__init__.py
BigDFT/check_examples.py
BigDFT/wahba.py
BigDFT/Database/Molecules.py
BigDFT/Database/__init__.py
BigDFT/Database/postprocess.yaml
BigDFT/Database/XYZs/AlF.xyz
BigDFT/Database/XYZs/Ar.xyz
BigDFT/Database/XYZs/BF.xyz
BigDFT/Database/XYZs/BH2.xyz
BigDFT/Database/XYZs/BH2Cl.xyz
BigDFT/Database/XYZs/BH2F.xyz
BigDFT/Database/XYZs/BH3.xyz
BigDFT/Database/XYZs/BHF2.xyz
BigDFT/Database/XYZs/BN.xyz
BigDFT/Database/XYZs/BO.xyz
BigDFT/Database/XYZs/BS.xyz
BigDFT/Database/XYZs/Be.xyz
BigDFT/Database/XYZs/BeH.xyz
BigDFT/Database/XYZs/BeH2.xyz
BigDFT/Database/XYZs/C2H.xyz
BigDFT/Database/XYZs/C2H2.xyz
BigDFT/Database/XYZs/C2H3.xyz
BigDFT/Database/XYZs/C2H4.xyz
BigDFT/Database/XYZs/C2H6O.xyz
BigDFT/Database/XYZs/C9H12.xyz
BigDFT/Database/XYZs/CH2-t.xyz
BigDFT/Database/XYZs/CH2.xyz
BigDFT/Database/XYZs/CH2BH.xyz
BigDFT/Database/XYZs/CH2F.xyz
BigDFT/Database/XYZs/CH2NH.xyz
BigDFT/Database/XYZs/CH2PH.xyz
BigDFT/Database/XYZs/CH3.xyz
BigDFT/Database/XYZs/CH3BH2.xyz
BigDFT/Database/XYZs/CH3Cl.xyz
BigDFT/Database/XYZs/CH3F.xyz
BigDFT/Database/XYZs/CH3NH2.xyz
BigDFT/Database/XYZs/CH3O.xyz
BigDFT/Database/XYZs/CH3OH.xyz
BigDFT/Database/XYZs/CH3SH.xyz
BigDFT/Database/XYZs/CH4.xyz
BigDFT/Database/XYZs/CN.xyz
BigDFT/Database/XYZs/CO.xyz
BigDFT/Database/XYZs/CO2.xyz
BigDFT/Database/XYZs/CS.xyz
BigDFT/Database/XYZs/CSO.xyz
BigDFT/Database/XYZs/Cl2.xyz
BigDFT/Database/XYZs/ClCN.xyz
BigDFT/Database/XYZs/ClF.xyz
BigDFT/Database/XYZs/F2.xyz
BigDFT/Database/XYZs/FCN.xyz
BigDFT/Database/XYZs/FCO.xyz
BigDFT/Database/XYZs/FH-OH.xyz
BigDFT/Database/XYZs/FNO.xyz
pybigdft-1.9.6.0.dist-info/METADATA
pybigdft-1.9.6.0.dist-info/WHEEL
pybigdft-1.9.6.0.dist-info/licenses/COPYING
pybigdft-1.9.6.0.dist-info/RECORD
