Metadata-Version: 2.4
Name: PyBigDFT
Version: 1.9.6.0
Summary: Python utilities for BigDFT
Project-URL: Homepage, https://bigdft.org
Project-URL: Bug Tracker, https://gitlab.com/l_sim/pybigdft/-/issues
Author-email: William Dawson <william.dawson@riken.jp>, Damien Caliste <Damien.Caliste@cea.fr>, Luigi Genovese <Luigi.Genovese@cea.fr>
License:                    GNU LESSER GENERAL PUBLIC LICENSE
License-File: COPYING
Classifier: License :: OSI Approved :: GNU General Public License v3 (GPLv3)
Classifier: Operating System :: OS Independent
Classifier: Programming Language :: Python :: 3
Requires-Python: >=3.6
Requires-Dist: numpy
Requires-Dist: pyfutile
Requires-Dist: pyyaml
Requires-Dist: scipy
Provides-Extra: materials
Requires-Dist: ase; extra == 'materials'
Requires-Dist: spglib; extra == 'materials'
Provides-Extra: viz
Requires-Dist: matplotlib; extra == 'viz'
Requires-Dist: py3dmol; extra == 'viz'
